selena_agent
