Metadata-Version: 1.0
Name: selena-agent
Version: 1.0.1
Summary: SelenaAgent - Selena monitoring agent.
Home-page: http://github.com/allegro/selena-agent
Author: Grupa Allegro Sp. z o.o. and Contributors
Author-email: it-ralph-dev@allegro.pl
License: Apache Software License v2.0
Platform: UNKNOWN
